candel_pos_ex_sar_forex_next3
